{
    "name": "Trulimero Trulicina",
    "short_name": "Trulimeo Trulrich",
    "height": "0.76 m",
    "weight": "14 kg",
    "hp": 65,
    "attack": 70,
    "defense": 65,
    "special_attack": 80,
    "special_defense": 75,
    "speed": 85,
    "lore": "\n\nLore of Trulimero Trulicina\n                                    \n\n\nTrulimero Trulicina represents a fascinating hybrid creature, combining the traits of a cat and a fish, while uniquely possessing human legs. This unusual appearance was triggered by an incident involving Bombardiro Crocodilo, who bombarded a nearby beach, leading to the emergence of Trulimero's distinctive form.\nIn earlier iterations of this meme, the character was depicted as an orange goldfish adorned with a cat's head. Notably, this version did not include any legs, presenting a simpler design compared to later adaptations.\nThe most recognizable incarnation of this meme showcases a striking silver fish paired with the head of a tabby cat, complete with four human legs. This captivating creature is said to inhabit a picturesque beach setting, further enriching the lore surrounding Trulimero Trulicina.\nDescription original text\nTrulimero Trulichima, il pretiletine in piscina, formaggio sulla trulalima, ma chi chiama la tazzina?\nTrulimero Trulrich, Protestin in the pool, cheese in Trulalima , but who calls a cup?\n\n"
}